[
    {
        "_id": "420e72a4-7a71-4045-b29d-a5a3f8aff4bf",
        "title": "table",
        "description": "a device with four legs and a flat surface."
    },
    {
        "_id": "ca82b568-870b-4417-9254-565eed59856d",
        "title": "table",
        "description": "a device with four legs and a flat surface."
    },
    {
        "_id": "be5a8de0-8a5b-4a3c-bd0b-03f4479e8356",
        "title": "table",
        "description": "a device with four legs and a flat surface."
    },
    {
        "_id": "2defee12-4434-44ae-9be3-6811fa093dc4",
        "title": "table",
        "description": "a device with four legs and a flat surface."
    },
    {
        "_id": "2af76073-50d3-4126-8bf5-6ec2fd9a3462",
        "title": "table",
        "description": "a device with four legs and a flat surface."
    },
    {
        "_id": "b7dcd383-251c-4bac-8764-7f25e37aa422",
        "title": "table",
        "description": "a device with four legs and a flat surface."
    }
]